qfactorjax/__init__.py
qfactorjax/qfactor.py
qfactorjax/qfactor_sample_jax.py
qfactorjax/singlelegedtensor.py
qfactorjax/unitary_acc.py
qfactorjax/unitarybuilderjax.py
qfactorjax/unitarymatrixjax.py
bqskit_qfactor_jax-1.0.1.dist-info/LICENSE
bqskit_qfactor_jax-1.0.1.dist-info/METADATA
bqskit_qfactor_jax-1.0.1.dist-info/WHEEL
bqskit_qfactor_jax-1.0.1.dist-info/top_level.txt
bqskit_qfactor_jax-1.0.1.dist-info/RECORD
