Metadata-Version: 2.1
Name: bqskit-qfactor-jax
Version: 1.0.1
Summary: QFactor GPU implementation in BQSKit using JAX
Home-page: https://github.com/BQSKit/bqskit-qfactor-jax
Author: Alon Kukliansky
License: BSD 3-Clause License
Project-URL: Bug Tracker, https://github.com/BQSKit/bqskit-qfactor-jax/issues
Project-URL: Source Code, https://github.com/BQSKit/bqskit-qfactor-jax
Project-URL: Documentation, https://bqskit.readthedocs.io/en/latest
Keywords: bqskit quantum partitioning qfactor instantiation
Classifier: Development Status :: 4 - Beta
Classifier: Environment :: Console
Classifier: Environment :: GPU
Classifier: Intended Audience :: Developers
Classifier: Intended Audience :: Education
Classifier: Intended Audience :: Science/Research
Classifier: License :: OSI Approved :: BSD License
Classifier: Operating System :: POSIX :: Linux
Classifier: Programming Language :: Python :: 3 :: Only
Classifier: Programming Language :: Python :: 3.9
Classifier: Programming Language :: Python :: 3.10
Classifier: Programming Language :: Python :: 3.11
Classifier: Programming Language :: Python :: 3.12
Classifier: Topic :: Scientific/Engineering
Classifier: Topic :: Scientific/Engineering :: Mathematics
Classifier: Topic :: Scientific/Engineering :: Physics
Classifier: Topic :: Software Development :: Compilers
Classifier: Typing :: Typed
Requires-Python: <4,>=3.9
License-File: LICENSE
Requires-Dist: numpy
Requires-Dist: bqskit>=1.1.0
Requires-Dist: typing-extensions>=4.0.0
Requires-Dist: jax[cuda12]
Requires-Dist: jaxlib
Requires-Dist: jaxtyping
